{"type":"PR","pr":{"number":27,"head":"f6206685b1af1c71165a08f6604f59d8bdb9ce67"},"user":"IILQ","status":"draft","branch":"cms/pages/accueil","collection":"pages","commitMessage":"Update Pages “accueil”","title":"Institut d'Innovation en Logistique du Québec | IIL","description":"L'IILQ vous offre des services d'aide technique, de recherche appliquée, de formation et de sensibilisation dans le domaine de la logistique auprès des PME du Québec.","objects":{"entry":{"path":"content/_index.md","sha":"6def104a1b00d82fcbf43727afdfa5d1fa37f103"},"files":[]},"timeStamp":"2020-01-31T15:48:06.383Z","version":"1"}